wtformvalidation/converter.py
wtformvalidation/__init__.py
WTFormValidation-1.0.0.dist-info/DESCRIPTION.rst
WTFormValidation-1.0.0.dist-info/METADATA
WTFormValidation-1.0.0.dist-info/metadata.json
WTFormValidation-1.0.0.dist-info/RECORD
WTFormValidation-1.0.0.dist-info/top_level.txt
WTFormValidation-1.0.0.dist-info/WHEEL
